airsimdroneracingvae/__init__.py
airsimdroneracingvae/client.py
airsimdroneracingvae/pfm.py
airsimdroneracingvae/types.py
airsimdroneracingvae/utils.py
airsimdroneracingvae-1.0.0.dist-info/DESCRIPTION.rst
airsimdroneracingvae-1.0.0.dist-info/METADATA
airsimdroneracingvae-1.0.0.dist-info/RECORD
airsimdroneracingvae-1.0.0.dist-info/WHEEL
airsimdroneracingvae-1.0.0.dist-info/metadata.json
airsimdroneracingvae-1.0.0.dist-info/top_level.txt
